README.md
setup.py
webpack_manifest/__init__.py
webpack_manifest/webpack_manifest.py
webpack_manifest.egg-info/PKG-INFO
webpack_manifest.egg-info/SOURCES.txt
webpack_manifest.egg-info/dependency_links.txt
webpack_manifest.egg-info/top_level.txt
webpack_manifest/templatetags/__init__.py
webpack_manifest/templatetags/webpack_manifest_tags.py