Metadata-Version: 1.0
Name: webpack-manifest
Version: 2.1.0
Summary: Manifest loader that allows you to include references to files built by webpack
Home-page: https://github.com/markfinger/python-webpack-manifest
Author: Mark Finger
Author-email: markfinger@gmail.com
License: UNKNOWN
Platform: UNKNOWN
